README.md
setup.py
mongoengine_user.egg-info/PKG-INFO
mongoengine_user.egg-info/SOURCES.txt
mongoengine_user.egg-info/dependency_links.txt
mongoengine_user.egg-info/requires.txt
mongoengine_user.egg-info/top_level.txt
mongoengineuser/__init__.py
mongoengineuser/models.py