Metadata-Version: 2.1
Name: mongoengine-user
Version: 0.0.2
Summary: Basic user models for mongoengine
Home-page: https://github.com/The-Nicholas-R-Barrow-Company-LLC/mongoengine-user
Author: The Nicholas R. Barrow Company, LLC
Author-email: me@nicholasrbarrow.com
License: MIT
Platform: UNKNOWN
Classifier: License :: OSI Approved :: MIT License
Classifier: Programming Language :: Python :: 3
Classifier: Programming Language :: Python :: 3.9
